nativelib-0.2.2.5.dist-info/RECORD
nativelib-0.2.2.5.dist-info/WHEEL
nativelib-0.2.2.5.dist-info/top_level.txt
nativelib-0.2.2.5.dist-info/METADATA
nativelib-0.2.2.5.dist-info/licenses/LICENSE
nativelib/__init__.py
nativelib/reader.py
nativelib/writer.py
nativelib/common/length.pxd
nativelib/common/cast_dataframes.pyx
nativelib/common/__init__.py
nativelib/common/cast_dataframes.cpython-314-darwin.so
nativelib/common/length.pyi
nativelib/common/length.cpython-314-darwin.so
nativelib/common/cast_dataframes.pyi
nativelib/common/defines.py
nativelib/common/cast_dataframes.pxd
nativelib/common/length.pyx
nativelib/common/blocks/writer.pyx
nativelib/common/blocks/writer.cpython-314-darwin.so
nativelib/common/blocks/reader.pyx
nativelib/common/blocks/__init__.py
nativelib/common/blocks/writer.pyi
nativelib/common/blocks/reader.pxd
nativelib/common/blocks/reader.pyi
nativelib/common/blocks/reader.cpython-314-darwin.so
nativelib/common/blocks/writer.pxd
nativelib/common/dtypes/parse.pxd
nativelib/common/dtypes/dtype.py
nativelib/common/dtypes/parse.pyi
nativelib/common/dtypes/__init__.py
nativelib/common/dtypes/parse.pyx
nativelib/common/dtypes/parse.cpython-314-darwin.so
nativelib/common/dtypes/objects/dtype.pyx
nativelib/common/dtypes/objects/lowcardinality.pyi
nativelib/common/dtypes/objects/array.cpython-314-darwin.so
nativelib/common/dtypes/objects/__init__.py
nativelib/common/dtypes/objects/array.pyx
nativelib/common/dtypes/objects/lowcardinality.pxd
nativelib/common/dtypes/objects/dtype.pyi
nativelib/common/dtypes/objects/lowcardinality.pyx
nativelib/common/dtypes/objects/array.pxd
nativelib/common/dtypes/objects/dtype.cpython-314-darwin.so
nativelib/common/dtypes/objects/lowcardinality.cpython-314-darwin.so
nativelib/common/dtypes/objects/array.pyi
nativelib/common/dtypes/objects/dtype.pxd
nativelib/common/dtypes/functions/decimals.pyi
nativelib/common/dtypes/functions/ipaddrs.pyx
nativelib/common/dtypes/functions/booleans.pyx
nativelib/common/dtypes/functions/uuids.pxd
nativelib/common/dtypes/functions/strings.pyi
nativelib/common/dtypes/functions/integers.pxd
nativelib/common/dtypes/functions/dates.pyx
