Metadata-Version: 2.4
Name: nativelib
Version: 0.2.2.5
Summary: Library for read and write clickhouse native format.
Author-email: 0xMihalich <bayanmobile87@gmail.com>
License: MIT License
Project-URL: Homepage, https://github.com/0xMihalich/nativelib
Project-URL: Documentation, https://github.com/0xMihalich/nativelib#readme
Project-URL: Repository, https://github.com/0xMihalich/nativelib
Project-URL: Changelog, https://github.com/0xMihalich/nativelib/blob/main/CHANGELOG.md
Classifier: Development Status :: 3 - Alpha
Classifier: Intended Audience :: Developers
Classifier: Programming Language :: Python :: 3.10
Classifier: Programming Language :: Python :: 3.11
Classifier: Programming Language :: Python :: 3.12
Classifier: Programming Language :: Python :: 3.13
Classifier: Programming Language :: Python :: 3.14
Requires-Python: >=3.10
License-File: LICENSE
Requires-Dist: backports.zoneinfo==0.2.1; python_version < "3.9"
Requires-Dist: pandas>=2.1.0
Requires-Dist: polars>=0.20.31
Dynamic: license-file
